wkdfh/__init__.py
wkdfh/base.py
wkdfh/items.py
wkdfh/queries.py
wkdfh-0.0.1.dist-info/LICENSE
wkdfh-0.0.1.dist-info/METADATA
wkdfh-0.0.1.dist-info/WHEEL
wkdfh-0.0.1.dist-info/top_level.txt
wkdfh-0.0.1.dist-info/RECORD
