Metadata-Version: 2.1
Name: wkdfh
Version: 0.0.1
Summary: Wikidata for humans
Home-page: https://github.com/bfontaine/wkdfh
Author: Baptiste Fontaine
Author-email: b@ptistefontaine.fr
License: Copyright © 2019 – Baptiste Fontaine
Requires-Dist: pywikibot
